yaco
