Metadata-Version: 1.0
Name: yaco.recipe.uwsgi
Version: 0.2.0
Summary: Buildout recipe for compiling uwsgi
Home-page: http://trac.yaco.es/cice-buscador
Author: Lorenzo Gil
Author-email: lgs@yaco.es
License: EUPL
Keywords: uwsgi buildout
Platform: UNKNOWN
Classifier: Development Status :: 4 - Beta
Classifier: Framework :: Buildout
